{
  "name": "EligibilityType",
  "fields": [
    {
      "fieldName": "eligibilityType",
      "fieldType": "String",
      "fieldValidateRules": ["required"]
    },
    {
      "fieldName": "description",
      "fieldType": "String"
    },
    {
      "fieldName": "hasExtraData",
      "fieldType": "Boolean"
    }
  ],
  "relationships": [],
  "changelogDate": "20210121104153",
  "entityTableName": "eligibility_type",
  "dto": "mapstruct",
  "pagination": "pagination",
  "service": "serviceClass",
  "jpaMetamodelFiltering": true,
  "fluentMethods": true,
  "readOnly": false,
  "embedded": false,
  "clientRootFolder": "",
  "applications": "*"
}
